prometheus_pacman_exporter.py
prometheus_pacman_exporter-0.0.3.dist-info/METADATA
prometheus_pacman_exporter-0.0.3.dist-info/WHEEL
prometheus_pacman_exporter-0.0.3.dist-info/entry_points.txt
prometheus_pacman_exporter-0.0.3.dist-info/top_level.txt
prometheus_pacman_exporter-0.0.3.dist-info/RECORD
