Metadata-Version: 2.1
Name: prometheus-pacman-exporter
Version: 0.0.3
Summary: Export pacman statistics to prometheus
Home-page: UNKNOWN
Author: Dennis Fink
Author-email: dennis.fink@c3l.lu
License: GPLv3+
Platform: any
Classifier: Development Status :: 5 - Production/Stable
Classifier: Programming Language :: Python
Classifier: Programming Language :: Python :: 3.7
Classifier: Environment :: Console
Classifier: Intended Audience :: System Administrators
Classifier: License :: OSI Approved :: GNU General Public License v3 or later (GPLv3+)
Classifier: Topic :: System :: Monitoring
Requires-Dist: prometheus-client
